gradio_webrtc/__init__.py
gradio_webrtc/credentials.py
gradio_webrtc/reply_on_pause.py
gradio_webrtc/reply_on_stopwords.py
gradio_webrtc/utils.py
gradio_webrtc/webrtc.py
gradio_webrtc/webrtc.pyi
gradio_webrtc/pause_detection/__init__.py
gradio_webrtc/pause_detection/vad.py
gradio_webrtc/speech_to_text/__init__.py
gradio_webrtc/speech_to_text/stt_.py
gradio_webrtc/templates/component/index.js
gradio_webrtc/templates/component/style.css
gradio_webrtc/templates/component/assets/worker-lPYB70QI.js
gradio_webrtc/templates/example/index.js
gradio_webrtc/templates/example/style.css
gradio_webrtc/templates/example/assets/worker-lPYB70QI.js
gradio_webrtc-0.0.30.dist-info/METADATA
gradio_webrtc-0.0.30.dist-info/WHEEL
gradio_webrtc-0.0.30.dist-info/licenses/LICENSE
gradio_webrtc-0.0.30.dist-info/RECORD
