Metadata-Version: 2.4
Name: gradio_webrtc
Version: 0.0.30
Summary: Stream images in realtime with webrtc
Author-email: Freddy Boulton <YOUREMAIL@domain.com>
License-Expression: Apache-2.0
License-File: LICENSE
Keywords: gradio-custom-component,gradio-template-Video,realtime,streaming,webrtc
Classifier: Development Status :: 3 - Alpha
Classifier: Operating System :: OS Independent
Classifier: Programming Language :: Python :: 3
Classifier: Programming Language :: Python :: 3 :: Only
Classifier: Programming Language :: Python :: 3.9
Classifier: Programming Language :: Python :: 3.10
Classifier: Programming Language :: Python :: 3.11
Classifier: Programming Language :: Python :: 3.12
Classifier: Topic :: Scientific/Engineering
Classifier: Topic :: Scientific/Engineering :: Artificial Intelligence
Classifier: Topic :: Scientific/Engineering :: Visualization
Requires-Python: >=3.10
Requires-Dist: aiortc
Requires-Dist: gradio<6.0,>=4.0
Provides-Extra: dev
Requires-Dist: build; extra == 'dev'
Requires-Dist: twine; extra == 'dev'
Provides-Extra: stopword
Requires-Dist: librosa; extra == 'stopword'
Requires-Dist: onnxruntime; extra == 'stopword'
Requires-Dist: silero; extra == 'stopword'
Provides-Extra: vad
Requires-Dist: librosa; extra == 'vad'
Requires-Dist: onnxruntime; extra == 'vad'
